aiocarrot/__init__.py
aiocarrot/__meta__.py
aiocarrot/carrot.py
aiocarrot/exceptions.py
aiocarrot/consumer/__init__.py
aiocarrot/consumer/consumer.py
aiocarrot/consumer/types.py
aiocarrot/consumer/utils.py
aiocarrot/scheduler/__init__.py
aiocarrot/scheduler/scheduler.py
aiocarrot/scheduler/types.py
aiocarrot-1.1.0.dist-info/METADATA
aiocarrot-1.1.0.dist-info/WHEEL
aiocarrot-1.1.0.dist-info/licenses/LICENSE
aiocarrot-1.1.0.dist-info/RECORD
