Metadata-Version: 2.4
Name: aiocarrot
Version: 1.1.0
Summary: Asynchronous framework for working with RabbitMQ
Project-URL: Repository, https://github.com/d3nbr0/aiocarrot
Author-email: Denis Shurygin <main@denbro.ru>
Maintainer-email: Denis Shurygin <main@denbro.ru>
License-Expression: MIT
License-File: LICENSE
Requires-Python: >=3.10
Requires-Dist: aio-pika<9.5,>=9.4.3
Requires-Dist: croniter>=6.0.0
Requires-Dist: loguru<0.8.0,>=0.7.2
Requires-Dist: pydantic<3.0.0,>=2.9.2
Requires-Dist: ujson>=5.10.0
Provides-Extra: test
Requires-Dist: pytest-asyncio~=0.24.0; extra == 'test'
Requires-Dist: pytest~=8.3.3; extra == 'test'
